gstui/__main__.py
gstui/gsclient.py
gstui/gstui.py
gstui/ui_base.py
gstui-0.1.4.dist-info/entry_points.txt
gstui-0.1.4.dist-info/LICENSE
gstui-0.1.4.dist-info/WHEEL
gstui-0.1.4.dist-info/METADATA
gstui-0.1.4.dist-info/RECORD
