Metadata-Version: 2.1
Name: gstui
Version: 0.1.4
Summary: Text User interface for exploring, downloading and uploading files to Google Cloud Storage buckets
License: MIT
Author: Matheus Fillipe
Author-email: matheusfillipeag@gmail.com
Requires-Python: >=3.10,<4.0
Classifier: License :: OSI Approved :: MIT License
Classifier: Programming Language :: Python :: 3
Classifier: Programming Language :: Python :: 3.10
Classifier: Programming Language :: Python :: 3.11
Requires-Dist: PyYAML (>=6.0,<7.0)
Requires-Dist: blessed (>=1.19.1,<2.0.0)
Requires-Dist: click (>=8.1.3,<9.0.0)
Requires-Dist: diskcache (>=5.4.0,<6.0.0)
Requires-Dist: google-cloud-storage (>=2.5.0,<3.0.0)
Requires-Dist: pyfzf (>=0.3.1,<0.4.0)
Requires-Dist: pytermgui (>=7.2.0,<8.0.0)
Requires-Dist: tqdm (>=4.64.1,<5.0.0)
